flask_konch/__init__.py
flask_konch/cli.py
flask_konch-3.0.0.dist-info/LICENSE
flask_konch-3.0.0.dist-info/METADATA
flask_konch-3.0.0.dist-info/WHEEL
flask_konch-3.0.0.dist-info/entry_points.txt
flask_konch-3.0.0.dist-info/top_level.txt
flask_konch-3.0.0.dist-info/RECORD
