Metadata-Version: 2.1
Name: flask-konch
Version: 3.0.0
Summary: An improved shell command for the Flask CLI
Home-page: https://github.com/sloria/flask-konch
Author: Steven Loria
Author-email: sloria1@gmail.com
License: MIT
Keywords: flask-konch
Classifier: Environment :: Web Environment
Classifier: Intended Audience :: Developers
Classifier: License :: OSI Approved :: MIT License
Classifier: Programming Language :: Python :: 3
Classifier: Programming Language :: Python :: 3.8
Classifier: Programming Language :: Python :: 3.9
Classifier: Programming Language :: Python :: 3.10
Classifier: Programming Language :: Python :: 3.11
Classifier: Programming Language :: Python :: 3.12
Classifier: Topic :: System :: Shells
Requires-Python: >=3.8
License-File: LICENSE
Requires-Dist: flask >=2.2.5
Requires-Dist: konch >=4
Provides-Extra: dev
Requires-Dist: pytest ; extra == 'dev'
Requires-Dist: flake8 ==7.0.0 ; extra == 'dev'
Requires-Dist: flake8-bugbear ==23.12.2 ; extra == 'dev'
Requires-Dist: pre-commit ~=3.6 ; extra == 'dev'
Requires-Dist: tox ; extra == 'dev'
Provides-Extra: lint
Requires-Dist: flake8 ==7.0.0 ; extra == 'lint'
Requires-Dist: flake8-bugbear ==23.12.2 ; extra == 'lint'
Requires-Dist: pre-commit ~=3.6 ; extra == 'lint'
Provides-Extra: tests
Requires-Dist: pytest ; extra == 'tests'
